engioptiqa/__init__.py
engioptiqa/annealing_solvers/__init__.py
engioptiqa/annealing_solvers/annealing_solver.py
engioptiqa/annealing_solvers/annealing_solver_amplify.py
engioptiqa/annealing_solvers/annealing_solver_dwave.py
engioptiqa/problems/__init__.py
engioptiqa/problems/solution_emulator.py
engioptiqa/problems/rod_1d/__init__.py
engioptiqa/problems/rod_1d/base_problem.py
engioptiqa/problems/rod_1d/design_optimization_problem.py
engioptiqa/problems/rod_1d/rod_1d.py
engioptiqa/problems/rod_1d/structural_analysis_problem.py
engioptiqa/variables/__init__.py
engioptiqa/variables/real_number.py
engioptiqa-0.2.2.dist-info/licenses/LICENSE
engioptiqa-0.2.2.dist-info/METADATA
engioptiqa-0.2.2.dist-info/WHEEL
engioptiqa-0.2.2.dist-info/top_level.txt
engioptiqa-0.2.2.dist-info/RECORD
