Metadata-Version: 2.4
Name: engioptiqa
Version: 0.2.2
Summary: Engineering Optimization with Quantum Annealing
Author-email: Fabian Key <fabian.key@tuwien.ac.at>
License-Expression: MIT
Project-URL: Homepage, https://github.com/EngiOptiQA/EngiOptiQA
Project-URL: Documentation, https://engioptiqa.github.io/EngiOptiQA/
Requires-Python: >=3.10
License-File: LICENSE
Requires-Dist: amplify[extra]==1.4.0
Requires-Dist: dwave-cloud-client==0.14.0
Requires-Dist: dwave-samplers==1.6.0
Requires-Dist: dwave-system==1.33.0
Requires-Dist: matplot2tikz==0.4.2
Requires-Dist: matplotlib==3.10.7
Requires-Dist: numpy==2.2.6
Requires-Dist: prettytable==3.16.0
Requires-Dist: sympy==1.14.0
Dynamic: license-file
